tkit_transformer_xl/__init__.py
tkit_transformer_xl/autoregressivewrapper.py
tkit_transformer_xl/transformer_xl.py
tkit_transformer_xl-0.0.0.6.dist-info/LICENSE
tkit_transformer_xl-0.0.0.6.dist-info/METADATA
tkit_transformer_xl-0.0.0.6.dist-info/WHEEL
tkit_transformer_xl-0.0.0.6.dist-info/top_level.txt
tkit_transformer_xl-0.0.0.6.dist-info/RECORD
