Metadata-Version: 2.1
Name: tkit-transformer-xl
Version: 0.0.0.6
Summary: Terry toolkit tkit_transformer_xl
Home-page: https://github.com/napoler/tkit_transformer_xl
Author: Terry Chan
Author-email: napoler2008@gmail.com
License: UNKNOWN
Platform: UNKNOWN
Requires-Dist: pytorch-lightning (>=1.2.10)
Requires-Dist: transformers (>=4.0.0)
Requires-Dist: memory-transformer-xl (>=0.1.0)
Requires-Dist: tkit-memory-performer-xl (>=0.0.1.0)
